pixivapi/__init__.py
pixivapi/client.py
pixivapi/common.py
pixivapi/enums.py
pixivapi/errors.py
pixivapi/models.py
pixiv_api-1.0.0.dist-info/LICENSE
pixiv_api-1.0.0.dist-info/WHEEL
pixiv_api-1.0.0.dist-info/METADATA
pixiv_api-1.0.0.dist-info/RECORD
