Metadata-Version: 2.1
Name: pixiv-api
Version: 1.0.0
Summary: A library for the Pixiv API.
Home-page: https://github.com/azuline/pixiv-api
License: Apache-2.0
Author: blissful
Author-email: blissful@sunsetglow.net
Requires-Python: >=3.6,<4.0
Classifier: License :: OSI Approved :: Apache Software License
Classifier: Programming Language :: Python :: 3
Classifier: Programming Language :: Python :: 3.6
Classifier: Programming Language :: Python :: 3.7
Classifier: Programming Language :: Python :: 3.8
Classifier: Programming Language :: Python :: 3.9
Requires-Dist: cloudscraper (>=1.2.48,<2.0.0)
Requires-Dist: requests (>=2.0.0,<3.0.0)
Project-URL: Repository, https://github.com/azuline/pixiv-api
